veedb/VERSION
veedb/__init__.py
veedb/client.py
veedb/exceptions.py
veedb/py.typed
veedb/schema_validator.py
veedb/test.py
veedb/apitypes/__init__.py
veedb/apitypes/common.py
veedb/apitypes/requests.py
veedb/apitypes/entities/__init__.py
veedb/apitypes/entities/character.py
veedb/apitypes/entities/producer.py
veedb/apitypes/entities/quote.py
veedb/apitypes/entities/release.py
veedb/apitypes/entities/staff.py
veedb/apitypes/entities/tag.py
veedb/apitypes/entities/trait.py
veedb/apitypes/entities/ulist.py
veedb/apitypes/entities/user.py
veedb/apitypes/entities/vn.py
veedb/methods/__init__.py
veedb/methods/fetch.py
veedb-0.1.7.dist-info/METADATA
veedb-0.1.7.dist-info/WHEEL
veedb-0.1.7.dist-info/top_level.txt
veedb-0.1.7.dist-info/RECORD
