Metadata-Version: 2.4
Name: veedb
Version: 0.1.7
Summary: An asynchronous Python wrapper for the VNDB API (Kana).
Home-page: https://github.com/Sub0X/veedb
Author: Sub01
Author-email: Sub01 <Sub01@subsoft.dev>
Maintainer-email: Sub01 <Sub01@subsoft.dev>
License: MIT
Project-URL: Homepage, https://github.com/Sub0X/veedb
Project-URL: Repository, https://github.com/Sub0X/veedb
Project-URL: Documentation, https://veedb.readthedocs.io/en/latest/
Project-URL: Bug Tracker, https://github.com/Sub0X/veedb/issues
Project-URL: Changelog, https://veedb.readthedocs.io/en/latest/changelog.html
Keywords: vndb,visual novel,api,async,wrapper
Classifier: Programming Language :: Python :: 3
Classifier: Programming Language :: Python :: 3.8
Classifier: Programming Language :: Python :: 3.9
Classifier: Programming Language :: Python :: 3.10
Classifier: Programming Language :: Python :: 3.11
Classifier: Programming Language :: Python :: 3.12
Classifier: License :: OSI Approved :: MIT License
Classifier: Operating System :: OS Independent
Classifier: Intended Audience :: Developers
Classifier: Topic :: Internet
Classifier: Topic :: Software Development :: Libraries :: Python Modules
Classifier: Topic :: Games/Entertainment
Classifier: Framework :: AsyncIO
Classifier: Development Status :: 4 - Beta
Requires-Python: >=3.8
Requires-Dist: aiohttp<5.0.0,>=3.8.0
Requires-Dist: dacite<2.0.0,>=1.6.0
Requires-Dist: orjson>=3.0.0
Dynamic: author
Dynamic: home-page
Dynamic: requires-python
